cellcube_xml_page_builder/__init__.py
cellcube_xml_page_builder/__main__.py
cellcube_xml_page_builder/cellcube_xml_builder.py
cellcube_xml_page_builder/cellcube_xml_elements.py
cellcube_xml_page_builder/example.py
cellcube_xml_page_builder-0.2.18.dist-info/LICENSE
cellcube_xml_page_builder-0.2.18.dist-info/METADATA
cellcube_xml_page_builder-0.2.18.dist-info/WHEEL
cellcube_xml_page_builder-0.2.18.dist-info/top_level.txt
cellcube_xml_page_builder-0.2.18.dist-info/RECORD
