Metadata-Version: 2.1
Name: cellcube-xml-page-builder
Version: 0.2.18
Summary: A Python library for cellcube xml pages generations
Home-page: https://github.com/fjamon/python-cellcube-page-builder
Author: François Joseph AMON D''ABY
Author-email: ange_amon@live.fr
License: UNKNOWN
Project-URL: Bug Tracker, https://github.com/fjamon/python-cellcube-page-builder/issues
Platform: UNKNOWN
Classifier: Programming Language :: Python :: 3
Classifier: License :: OSI Approved :: MIT License
Classifier: Operating System :: OS Independent
Requires-Python: >=3.6
License-File: LICENSE
Requires-Dist: requests
Requires-Dist: beautifulsoup4
